MANIFEST.in
README.rst
setup.py
DIWNotifier.egg-info/PKG-INFO
DIWNotifier.egg-info/SOURCES.txt
DIWNotifier.egg-info/dependency_links.txt
DIWNotifier.egg-info/requires.txt
DIWNotifier.egg-info/top_level.txt
bin/diwnotifier
diwnotifier/diwnotifier.py
diwnotifier/settings.py
diwnotifier/taskbar_icon.py
diwnotifier/scraping/__init__.py
diwnotifier/scraping/session.py
diwnotifier/scraping/web_parser.py
diwnotifier/utils/__init__.py
diwnotifier/utils/threads_collector.py
diwnotifier/utils/utils.py
diwnotifier/utils/short_links_collector/__init__.py
diwnotifier/utils/short_links_collector/short_links_collector.py
diwnotifier/utils/short_links_collector/tiny4py/__init__.py
diwnotifier/utils/short_links_collector/tiny4py/tiny4py.py
diwnotifier/utils/short_links_collector/tiny4py/shorteners/__init__.py
diwnotifier/utils/short_links_collector/tiny4py/shorteners/bitly_shortener.py
diwnotifier/utils/short_links_collector/tiny4py/shorteners/consts.py
diwnotifier/utils/short_links_collector/tiny4py/shorteners/google_shortener.py
diwnotifier/utils/short_links_collector/tiny4py/shorteners/qrcode.py
diwnotifier/utils/short_links_collector/tiny4py/shorteners/shortener.py
diwnotifier/utils/short_links_collector/tiny4py/shorteners/shortener_error.py
diwnotifier/utils/short_links_collector/tiny4py/shorteners/shortener_qrcode.py
diwnotifier/utils/short_links_collector/tiny4py/shorteners/tinyurl_shortener.py