Metadata-Version: 1.1
Name: DIWNotifier
Version: 0.9.2
Summary: A featureful web crawler for http://clandiw.it site
Home-page: https://pypi.python.org/pypi/DIWNotifier/
Author: am0n
Author-email: am0n@clandiw.it
License: LICENSE.txt
Keywords: ipb clandiw scraping forum
Platform: Debian 7.0 - Wheezy
Classifier: License :: OSI Approved :: GNU General Public License (GPL)
Classifier: Operating System :: POSIX :: Linux
Classifier: Programming Language :: Python :: 2.7
